LICENSE
README.md
setup.py
fibo_crypt/__init__.py
fibo_crypt/decryption.py
fibo_crypt/encryption.py
fibo_crypt/key_generator.py
fibo_crypt.egg-info/PKG-INFO
fibo_crypt.egg-info/SOURCES.txt
fibo_crypt.egg-info/dependency_links.txt
fibo_crypt.egg-info/top_level.txt