Metadata-Version: 2.1
Name: fibo_crypt
Version: 0.1
Summary: A package for encryption and decryption using Fibonacci sequence
Author: Samer Makni
Author-email: samermakni@outlook.com
Classifier: Development Status :: 3 - Alpha
Classifier: Intended Audience :: Developers
Classifier: License :: OSI Approved :: MIT License
Classifier: Programming Language :: Python :: 3
Classifier: Programming Language :: Python :: 3.6
Classifier: Programming Language :: Python :: 3.7
Classifier: Programming Language :: Python :: 3.8
Classifier: Programming Language :: Python :: 3.9
License-File: LICENSE
